click_fish.py
setup.cfg
setup.py
click_fish.egg-info/PKG-INFO
click_fish.egg-info/SOURCES.txt
click_fish.egg-info/dependency_links.txt
click_fish.egg-info/requires.txt
click_fish.egg-info/top_level.txt