Metadata-Version: 1.0
Name: click-fish
Version: 0.1.0
Summary: Fish completion for Click
Home-page: https://github.com/glehmann/click-fish
Author: Gaëtan Lehmann
Author-email: gaetan.lehmann@gmail.com
License: MIT
Platform: UNKNOWN
